stupyd/__init__.py
stupyd/main.py
stupyd/compiler/__init__.py
stupyd/compiler/extendListener.py
stupyd/compiler/stuPydLexer.py
stupyd/compiler/stuPydListener.py
stupyd/compiler/stuPydParser.py
stupyd/interpreter/__init__.py
stupyd/interpreter/stupydInterpreter.py
stupyd/interpreter/stupydShell.py
stupyd-0.0.2.dist-info/METADATA
stupyd-0.0.2.dist-info/RECORD
stupyd-0.0.2.dist-info/WHEEL
stupyd-0.0.2.dist-info/entry_points.txt
stupyd-0.0.2.dist-info/top_level.txt
stupyd-0.0.2.dist-info/zip-safe
