Metadata-Version: 2.1
Name: stupyd
Version: 0.0.2
Summary: official stupyd programming language package
Home-page: https://github.com/StuPyd/stupyd-lang
Author: stupyd group
Author-email: sunmch15@foxmail.com
License: Apache
Keywords: python stupyd education programming language
Platform: UNKNOWN
Classifier: Programming Language :: Python :: 3
Requires-Dist: antlr4-python3-runtime (>=4.7.1)
